		<!--<Territory>
			<Name>test_ambient_vehicle</Name>
			<Districts>
				<District>
					<Name>ped_spawn_test</Name>
					<Control>100</Control>
					<Control_max>100</Control_max>
					<Morale>0</Morale>
					<Morale_max>100</Morale_max>
					<Grid_index></Grid_index>
					<Grid_color>
						<R>255</R>
						<G>255</G>
						<B>255</B>
					</Grid_color>
					<Display_name></Display_name>
					<liberated_tech>0.0</liberated_tech>
					<liberated_marauder>0.0</liberated_marauder>
					<liberated_edf>0</liberated_edf>
					<DiscLayer>Layer 0</DiscLayer>
					<district_index>0</district_index>
					<min_progression_edf>0</min_progression_edf>
					<VFX_tint>
						<R>255</R>
						<G>255</G>
						<B>255</B>
					</VFX_tint>
					<District_Flags></District_Flags>
				</District>
			</Districts>
			<_Editor>
				<Category>Entries</Category>
			</_Editor>
			<StreamingParams>
				<VerticalMask></VerticalMask>
				<HorizMask></HorizMask>
			</StreamingParams>
			<territory_index>0</territory_index>
		</Territory>
		<Territory>
			<Name>test_raid</Name>
			<Districts>
				<District>
					<Name>ped_spawn_test</Name>
					<Control>100</Control>
					<Control_max>100</Control_max>
					<Morale>0</Morale>
					<Morale_max>100</Morale_max>
					<Grid_index></Grid_index>
					<Grid_color>
						<R>255</R>
						<G>255</G>
						<B>255</B>
					</Grid_color>
					<Display_name></Display_name>
					<liberated_tech>0.0</liberated_tech>
					<liberated_marauder>0.0</liberated_marauder>
					<liberated_edf>0</liberated_edf>
					<DiscLayer>Layer 0</DiscLayer>
					<district_index>0</district_index>
					<min_progression_edf>0</min_progression_edf>
					<VFX_tint>
						<R>255</R>
						<G>255</G>
						<B>255</B>
					</VFX_tint>
					<District_Flags></District_Flags>
				</District>
			</Districts>
			<_Editor>
				<Category>Entries</Category>
			</_Editor>
			<StreamingParams>
				<VerticalMask></VerticalMask>
				<HorizMask></HorizMask>
			</StreamingParams>
			<territory_index>0</territory_index>
		</Territory>
		<Territory>
			<Name>test_house_arrest</Name>
			<Districts>
				<District>
					<Name>ped_spawn_test</Name>
					<Control>100</Control>
					<Control_max>100</Control_max>
					<Morale>0</Morale>
					<Morale_max>100</Morale_max>
					<Grid_index></Grid_index>
					<Grid_color>
						<R>255</R>
						<G>255</G>
						<B>255</B>
					</Grid_color>
					<Display_name></Display_name>
					<liberated_tech>0.0</liberated_tech>
					<liberated_marauder>0.0</liberated_marauder>
					<liberated_edf>0</liberated_edf>
					<DiscLayer>Layer 0</DiscLayer>
					<district_index>0</district_index>
					<min_progression_edf>0</min_progression_edf>
					<VFX_tint>
						<R>255</R>
						<G>255</G>
						<B>255</B>
					</VFX_tint>
					<District_Flags></District_Flags>
				</District>
			</Districts>
			<_Editor>
				<Category>Entries</Category>
			</_Editor>
			<StreamingParams>
				<VerticalMask></VerticalMask>
				<HorizMask></HorizMask>
			</StreamingParams>
			<territory_index>0</territory_index>
		</Territory>
		<Territory>
			<Name>test_luke_ow</Name>
			<Districts>
				<District>
					<Name>Wastelands</Name>
					<Control>500</Control>
					<Control_max>500</Control_max>
					<Morale>30</Morale>
					<Morale_max>500</Morale_max>
					<Grid_index></Grid_index>
					<Grid_color>
						<R>255</R>
						<G>255</G>
						<B>255</B>
					</Grid_color>
					<Display_name></Display_name>
					<liberated_tech>0.0</liberated_tech>
					<liberated_marauder>0.0</liberated_marauder>
					<liberated_edf>0</liberated_edf>
					<DiscLayer>Layer 0</DiscLayer>
					<district_index>0</district_index>
					<min_progression_edf>0</min_progression_edf>
					<VFX_tint>
						<R>255</R>
						<G>255</G>
						<B>255</B>
					</VFX_tint>
					<District_Flags></District_Flags>
				</District>
			</Districts>
			<_Editor>
				<Category>Entries</Category>
			</_Editor>
			<StreamingParams>
				<VerticalMask></VerticalMask>
				<HorizMask></HorizMask>
			</StreamingParams>
			<territory_index>0</territory_index>
		</Territory>
		<Territory>
			<Name>test_house_arrest</Name>
			<Districts>
				<District>
					<Name>ped_spawn_test</Name>
					<Control>100</Control>
					<Control_max>100</Control_max>
					<Morale>0</Morale>
					<Morale_max>100</Morale_max>
					<Grid_index></Grid_index>
					<Grid_color>
						<R>255</R>
						<G>255</G>
						<B>255</B>
					</Grid_color>
					<Display_name></Display_name>
					<liberated_tech>0.0</liberated_tech>
					<liberated_marauder>0.0</liberated_marauder>
					<liberated_edf>0</liberated_edf>
					<DiscLayer>Layer 0</DiscLayer>
					<district_index>0</district_index>
					<min_progression_edf>0</min_progression_edf>
					<VFX_tint>
						<R>255</R>
						<G>255</G>
						<B>255</B>
					</VFX_tint>
					<District_Flags></District_Flags>
				</District>
			</Districts>
			<_Editor>
				<Category>Entries</Category>
			</_Editor>
			<StreamingParams>
				<VerticalMask></VerticalMask>
				<HorizMask></HorizMask>
			</StreamingParams>
			<territory_index>0</territory_index>
		</Territory>
		<Territory>
			<Name>test_assassin</Name>
			<Districts>
				<District>
					<Name>ped_spawn_test</Name>
					<Control>100</Control>
					<Control_max>100</Control_max>
					<Morale>0</Morale>
					<Morale_max>100</Morale_max>
					<Grid_index></Grid_index>
					<Grid_color>
						<R>255</R>
						<G>255</G>
						<B>255</B>
					</Grid_color>
					<Display_name></Display_name>
					<liberated_tech>0.0</liberated_tech>
					<liberated_marauder>0.0</liberated_marauder>
					<liberated_edf>0</liberated_edf>
					<DiscLayer>Layer 0</DiscLayer>
					<district_index>0</district_index>
					<min_progression_edf>0</min_progression_edf>
					<VFX_tint>
						<R>255</R>
						<G>255</G>
						<B>255</B>
					</VFX_tint>
					<District_Flags></District_Flags>
				</District>
			</Districts>
			<_Editor>
				<Category>Entries</Category>
			</_Editor>
			<StreamingParams>
				<VerticalMask></VerticalMask>
				<HorizMask></HorizMask>
			</StreamingParams>
			<territory_index>0</territory_index>
		</Territory>
		<Territory>
			<Name>test_dfried_ambient</Name>
			<Districts>
				<District>
					<Name>test_dfried_ambient</Name>
					<Control>100</Control>
					<Control_max>100</Control_max>
					<Morale>0</Morale>
					<Morale_max>100</Morale_max>
					<Grid_index></Grid_index>
					<Grid_color>
						<R>255</R>
						<G>255</G>
						<B>255</B>
					</Grid_color>
					<Display_name></Display_name>
					<liberated_tech>0.0</liberated_tech>
					<liberated_marauder>0.0</liberated_marauder>
					<liberated_edf>0</liberated_edf>
					<DiscLayer>Layer 0</DiscLayer>
					<district_index>0</district_index>
					<min_progression_edf>0</min_progression_edf>
					<VFX_tint>
						<R>255</R>
						<G>255</G>
						<B>255</B>
					</VFX_tint>
					<District_Flags></District_Flags>
				</District>
			</Districts>
			<_Editor>
				<Category>Entries</Category>
			</_Editor>
			<StreamingParams>
				<VerticalMask></VerticalMask>
				<HorizMask></HorizMask>
			</StreamingParams>
			<territory_index>0</territory_index>
		</Territory>
		<Territory>
			<Name>test_rob_tech_level</Name>
			<Districts>
				<District>
					<Name>test_rob_tech_level</Name>
					<Control>100</Control>
					<Control_max>100</Control_max>
					<Morale>0</Morale>
					<Morale_max>100</Morale_max>
					<Grid_index></Grid_index>
					<Grid_color>
						<R>255</R>
						<G>255</G>
						<B>255</B>
					</Grid_color>
					<Display_name></Display_name>
					<liberated_tech>0.0</liberated_tech>
					<liberated_marauder>0.0</liberated_marauder>
					<liberated_edf>0</liberated_edf>
					<DiscLayer>Layer 0</DiscLayer>
					<district_index>0</district_index>
					<min_progression_edf>0</min_progression_edf>
					<VFX_tint>
						<R>255</R>
						<G>255</G>
						<B>255</B>
					</VFX_tint>
					<District_Flags></District_Flags>
				</District>
			</Districts>
			<Tech_level>1.5</Tech_level>
			<Tech_level_max>3.0</Tech_level_max>
			<_Editor>
				<Category>Entries</Category>
			</_Editor>
			<StreamingParams>
				<VerticalMask></VerticalMask>
				<HorizMask></HorizMask>
			</StreamingParams>
			<territory_index>0</territory_index>
		</Territory>
		<Territory>
			<Name>test_activity_spawn</Name>
			<Districts>
				<District>
					<Name>test_activity_spawn</Name>
					<Control>100</Control>
					<Control_max>100</Control_max>
					<Morale>0</Morale>
					<Morale_max>100</Morale_max>
					<Grid_index></Grid_index>
					<Grid_color>
						<R>255</R>
						<G>128</G>
						<B>0</B>
					</Grid_color>
					<Display_name></Display_name>
					<liberated_tech>0.0</liberated_tech>
					<liberated_marauder>0.0</liberated_marauder>
					<liberated_edf>0</liberated_edf>
					<DiscLayer>Layer 0</DiscLayer>
					<district_index>0</district_index>
					<min_progression_edf>0</min_progression_edf>
					<VFX_tint>
						<R>255</R>
						<G>255</G>
						<B>255</B>
					</VFX_tint>
					<District_Flags></District_Flags>
				</District>
			</Districts>
			<_Editor>
				<Category>Entries</Category>
			</_Editor>
			<StreamingParams>
				<VerticalMask></VerticalMask>
				<HorizMask></HorizMask>
			</StreamingParams>
			<territory_index>0</territory_index>
		</Territory>
		<Territory>
			<Name>test_safehouse</Name>
			<Districts>
				<District>
					<Name>test1</Name>
					<Control>100</Control>
					<Control_max>100</Control_max>
					<Morale>0</Morale>
					<Morale_max>100</Morale_max>
					<Grid_index></Grid_index>
					<Grid_color>
						<R>255</R>
						<G>255</G>
						<B>255</B>
					</Grid_color>
					<Display_name></Display_name>
					<liberated_tech>0.0</liberated_tech>
					<liberated_marauder>0.0</liberated_marauder>
					<liberated_edf>0</liberated_edf>
					<DiscLayer>Layer 0</DiscLayer>
					<district_index>0</district_index>
					<min_progression_edf>0</min_progression_edf>
					<VFX_tint>
						<R>255</R>
						<G>255</G>
						<B>255</B>
					</VFX_tint>
					<District_Flags></District_Flags>
				</District>
				<District>
					<Name>test2</Name>
					<Control>100</Control>
					<Control_max>100</Control_max>
					<Morale>0</Morale>
					<Morale_max>100</Morale_max>
					<Grid_index></Grid_index>
					<Grid_color>
						<R>255</R>
						<G>255</G>
						<B>255</B>
					</Grid_color>
					<Display_name></Display_name>
					<liberated_tech>0.0</liberated_tech>
					<liberated_marauder>0.0</liberated_marauder>
					<liberated_edf>0</liberated_edf>
					<DiscLayer>Layer 0</DiscLayer>
					<district_index>0</district_index>
					<min_progression_edf>0</min_progression_edf>
					<VFX_tint>
						<R>255</R>
						<G>255</G>
						<B>255</B>
					</VFX_tint>
					<District_Flags></District_Flags>
				</District>
			</Districts>
			<_Editor>
				<Category>Entries</Category>
			</_Editor>
			<StreamingParams>
				<VerticalMask></VerticalMask>
				<HorizMask></HorizMask>
			</StreamingParams>
			<territory_index>0</territory_index>
		</Territory>
		<Territory>
			<Name>test_mg_rs</Name>
			<Districts>
				<District>
					<Name>ride_shot</Name>
					<Control>100</Control>
					<Control_max>100</Control_max>
					<Morale>0</Morale>
					<Morale_max>100</Morale_max>
					<Grid_index>
						<Grid_item>
							<Index>0101</Index>
							<Grid_flags></Grid_flags>
						</Grid_item>
					</Grid_index>
					<Grid_color>
						<R>255</R>
						<G>255</G>
						<B>255</B>
					</Grid_color>
					<Display_name></Display_name>
					<liberated_tech>0.0</liberated_tech>
					<liberated_marauder>0.0</liberated_marauder>
					<liberated_edf>0</liberated_edf>
					<DiscLayer>Layer 0</DiscLayer>
					<district_index>0</district_index>
					<min_progression_edf>0</min_progression_edf>
					<VFX_tint>
						<R>255</R>
						<G>255</G>
						<B>255</B>
					</VFX_tint>
					<District_Flags></District_Flags>
				</District>
			</Districts>
			<_Editor>
				<Category>Entries</Category>
			</_Editor>
			<StreamingParams>
				<VerticalMask></VerticalMask>
				<HorizMask></HorizMask>
			</StreamingParams>
			<territory_index>0</territory_index>
		</Territory>
		<Territory>
			<Name>test_dummy</Name>
			<Districts>
				<District>
					<Name>test_dummy</Name>
					<Control>100</Control>
					<Control_max>100</Control_max>
					<Morale>0</Morale>
					<Morale_max>100</Morale_max>
					<Grid_index></Grid_index>
					<Grid_color>
						<R>255</R>
						<G>255</G>
						<B>255</B>
					</Grid_color>
					<Display_name></Display_name>
					<liberated_tech>0.0</liberated_tech>
					<liberated_marauder>0.0</liberated_marauder>
					<liberated_edf>0</liberated_edf>
					<DiscLayer>Layer 0</DiscLayer>
					<district_index>0</district_index>
					<min_progression_edf>0</min_progression_edf>
					<VFX_tint>
						<R>255</R>
						<G>255</G>
						<B>255</B>
					</VFX_tint>
					<District_Flags></District_Flags>
				</District>
			</Districts>
			<_Editor>
				<Category>Entries</Category>
			</_Editor>
			<StreamingParams>
				<VerticalMask></VerticalMask>
				<HorizMask></HorizMask>
			</StreamingParams>
			<territory_index>0</territory_index>
		</Territory>-->
				<!--<Territory>
			<Name>test_mab</Name>
			<Districts>
				<District>
					<Name>dust</Name>
					<Display_name>TERR_DUST</Display_name>
					<Control>100</Control>
					<Control_max>100</Control_max>
					<Morale>0</Morale>
					<Morale_max>100</Morale_max>
					<liberated_tech>0.0</liberated_tech>
					<liberated_marauder>0.0</liberated_marauder>
					<liberated_edf>0</liberated_edf>
					<Grid_index>
						<Grid_item>
							<Index>0808</Index>
							<Grid_flags></Grid_flags>
						</Grid_item>
					</Grid_index>
					<Grid_color>
						<R>255</R>
						<G>255</G>
						<B>255</B>
					</Grid_color>
					<DiscLayer>Layer 0</DiscLayer>
					<district_index>1</district_index>
					<min_progression_edf>0</min_progression_edf>
					<VFX_tint>
						<R>255</R>
						<G>255</G>
						<B>255</B>
					</VFX_tint>
					<District_Flags></District_Flags>
				</District>
			</Districts>
			<_Editor>
				<Category>Entries</Category>
			</_Editor>
			<StreamingParams>
				<VerticalMask></VerticalMask>
				<HorizMask></HorizMask>
			</StreamingParams>
			<territory_index>0</territory_index>
		</Territory>-->
		
		<!--		<Territory>
			<Name>test_ambient_spawn</Name>
			<Districts>
				<District>
					<Name>ped_spawn_test</Name>
					<Control>100</Control>
					<Control_max>100</Control_max>
					<Morale>0</Morale>
					<Morale_max>100</Morale_max>
					<Grid_index></Grid_index>
					<Grid_color>
						<R>255</R>
						<G>255</G>
						<B>255</B>
					</Grid_color>
					<Display_name></Display_name>
					<liberated_tech>0.0</liberated_tech>
					<liberated_marauder>0.0</liberated_marauder>
					<liberated_edf>0</liberated_edf>
					<DiscLayer>Layer 0</DiscLayer>
					<district_index>0</district_index>
					<min_progression_edf>0</min_progression_edf>
					<VFX_tint>
						<R>255</R>
						<G>255</G>
						<B>255</B>
					</VFX_tint>
					<District_Flags></District_Flags>
				</District>
			</Districts>
			<_Editor>
				<Category>Entries</Category>
			</_Editor>
			<StreamingParams>
				<VerticalMask></VerticalMask>
				<HorizMask></HorizMask>
			</StreamingParams>
			<territory_index>0</territory_index>
		</Territory>-->
		<!--<Territory>
			<Name>test_luke_ambient</Name>
			<Districts>
				<District>
					<Name>spawning_test</Name>
					<Control>100</Control>
					<Control_max>100</Control_max>
					<Morale>0</Morale>
					<Morale_max>100</Morale_max>
					<Grid_index></Grid_index>
					<Grid_color>
						<R>255</R>
						<G>255</G>
						<B>255</B>
					</Grid_color>
					<Display_name></Display_name>
					<liberated_tech>0.0</liberated_tech>
					<liberated_marauder>0.0</liberated_marauder>
					<liberated_edf>0</liberated_edf>
					<DiscLayer>Layer 0</DiscLayer>
					<district_index>0</district_index>
					<min_progression_edf>0</min_progression_edf>
					<VFX_tint>
						<R>255</R>
						<G>255</G>
						<B>255</B>
					</VFX_tint>
					<District_Flags></District_Flags>
				</District>
			</Districts>
			<_Editor>
				<Category>Entries</Category>
			</_Editor>
			<StreamingParams>
				<VerticalMask></VerticalMask>
				<HorizMask></HorizMask>
			</StreamingParams>
			<territory_index>0</territory_index>
		</Territory>-->
		
		<!--		<Territory>
			<Name>jeffk_territory</Name>
			<Districts>
				<District>
					<Name>test_jeffk_Origin</Name>
					<Control>1000</Control>
					<Control_max>1000</Control_max>
					<Morale>0</Morale>
					<Morale_max>100</Morale_max>
					<Grid_index></Grid_index>
					<Grid_color>
						<R>255</R>
						<G>255</G>
						<B>255</B>
					</Grid_color>
					<Display_name></Display_name>
					<liberated_tech>0.0</liberated_tech>
					<liberated_marauder>0.0</liberated_marauder>
					<liberated_edf>0</liberated_edf>
					<DiscLayer>Layer 0</DiscLayer>
					<district_index>0</district_index>
					<min_progression_edf>0</min_progression_edf>
					<VFX_tint>
						<R>255</R>
						<G>255</G>
						<B>255</B>
					</VFX_tint>
					<District_Flags></District_Flags>
				</District>
				<District>
					<Name>test_jeffk_Excess</Name>
					<Control>100</Control>
					<Control_max>1000</Control_max>
					<Morale>50</Morale>
					<Morale_max>1000</Morale_max>
					<Grid_index></Grid_index>
					<Grid_color>
						<R>255</R>
						<G>255</G>
						<B>255</B>
					</Grid_color>
					<Display_name></Display_name>
					<liberated_tech>0.0</liberated_tech>
					<liberated_marauder>0.0</liberated_marauder>
					<liberated_edf>0</liberated_edf>
					<DiscLayer>Layer 0</DiscLayer>
					<district_index>0</district_index>
					<min_progression_edf>0</min_progression_edf>
					<VFX_tint>
						<R>255</R>
						<G>255</G>
						<B>255</B>
					</VFX_tint>
					<District_Flags></District_Flags>
				</District>
			</Districts>
			<_Editor>
				<Category>Entries</Category>
			</_Editor>
			<StreamingParams>
				<VerticalMask></VerticalMask>
				<HorizMask></HorizMask>
			</StreamingParams>
			<territory_index>0</territory_index>
		</Territory>-->